edc_permissions/__init__.py
edc_permissions/apps.py
edc_permissions/default_codenames_by_group.py
edc_permissions/group_names.py
edc_permissions/models.py
edc_permissions/urls.py
edc_permissions/codename_tuples/__init__.py
edc_permissions/codename_tuples/dashboard_tuples.py
edc_permissions/codename_tuples/navbar_tuples.py
edc_permissions/codename_tuples/rando_tuples.py
edc_permissions/codenames/__init__.py
edc_permissions/codenames/account_manager.py
edc_permissions/codenames/action_items.py
edc_permissions/codenames/administration.py
edc_permissions/codenames/ae.py
edc_permissions/codenames/ae_review.py
edc_permissions/codenames/auditor.py
edc_permissions/codenames/celery_manager.py
edc_permissions/codenames/clinic.py
edc_permissions/codenames/dashboard.py
edc_permissions/codenames/data_manager.py
edc_permissions/codenames/data_query.py
edc_permissions/codenames/everyone.py
edc_permissions/codenames/export.py
edc_permissions/codenames/lab.py
edc_permissions/codenames/lab_view.py
edc_permissions/codenames/navbars.py
edc_permissions/codenames/pharmacy.py
edc_permissions/codenames/pii.py
edc_permissions/codenames/pii_view.py
edc_permissions/codenames/rando.py
edc_permissions/codenames/screening.py
edc_permissions/codenames/site_data_manager.py
edc_permissions/codenames/tmg.py
edc_permissions/tests/__init__.py
edc_permissions/tests/models.py
edc_permissions/tests/test_permissions.py
edc_permissions/tests/urls.py
edc_permissions/update/__init__.py
edc_permissions/update/constants.py
edc_permissions/update/update_group_permissions.py
edc_permissions/update/utils.py
edc_permissions-0.1.48.dist-info/LICENSE
edc_permissions-0.1.48.dist-info/METADATA
edc_permissions-0.1.48.dist-info/WHEEL
edc_permissions-0.1.48.dist-info/top_level.txt
edc_permissions-0.1.48.dist-info/RECORD
